mkdocsthemebootstrap4/404.html
mkdocsthemebootstrap4/__init__.py
mkdocsthemebootstrap4/base.html
mkdocsthemebootstrap4/content.html
mkdocsthemebootstrap4/main.html
mkdocsthemebootstrap4/mkdocs_theme.yml
mkdocsthemebootstrap4/nav-sub.html
mkdocsthemebootstrap4/plugin.py
mkdocsthemebootstrap4/search-modal.html
mkdocsthemebootstrap4/toc.html
mkdocsthemebootstrap4/dist/bundle.js
mkdocs_theme_bootstrap4-0.4.0.dist-info/LICENSE.md
mkdocs_theme_bootstrap4-0.4.0.dist-info/METADATA
mkdocs_theme_bootstrap4-0.4.0.dist-info/WHEEL
mkdocs_theme_bootstrap4-0.4.0.dist-info/entry_points.txt
mkdocs_theme_bootstrap4-0.4.0.dist-info/top_level.txt
mkdocs_theme_bootstrap4-0.4.0.dist-info/RECORD
