Metadata-Version: 2.1
Name: mkdocs-theme-bootstrap4
Version: 0.4.0
Summary: A vanilla Bootstrap 4 theme
Home-page: https://github.com/LukeCarrier/mkdocs-theme-bootstrap4
Author: Luke Carrier
Author-email: luke@carrier.im
License: MIT
Platform: UNKNOWN
Requires-Dist: mkdocs (>=1.0)
